oncocyrix_multicohort/__init__.py
oncocyrix_multicohort/pipeline.py
oncocyrix_multicohort-0.1.0.dist-info/METADATA
oncocyrix_multicohort-0.1.0.dist-info/WHEEL
oncocyrix_multicohort-0.1.0.dist-info/entry_points.txt
oncocyrix_multicohort-0.1.0.dist-info/top_level.txt
oncocyrix_multicohort-0.1.0.dist-info/RECORD
