Metadata-Version: 2.4
Name: oncocyrix-multicohort
Version: 0.1.0
Summary: Single-cell RNA-seq multicohort analysis pipeline with Scanpy (10x-only, CAR-T aware, structured outputs)
Author: Sheryar Malik
License: MIT
Keywords: single-cell,scRNA-seq,scanpy,anndata,10x,multicohort,celltypist,bbknn,deseq2,gseapy,CAR-T
Classifier: Development Status :: 3 - Alpha
Classifier: Intended Audience :: Science/Research
Classifier: License :: OSI Approved :: MIT License
Classifier: Programming Language :: Python :: 3
Classifier: Programming Language :: Python :: 3.9
Classifier: Programming Language :: Python :: 3.10
Classifier: Programming Language :: Python :: 3.11
Classifier: Topic :: Scientific/Engineering :: Bio-Informatics
Requires-Python: >=3.9
Requires-Dist: scanpy>=1.9.6
Requires-Dist: anndata>=0.9.2
Requires-Dist: numpy>=1.23
Requires-Dist: pandas>=1.5
Requires-Dist: scipy>=1.9
Requires-Dist: matplotlib>=3.7
Requires-Dist: openpyxl>=3.1
Requires-Dist: tqdm>=4.66
Provides-Extra: mygene
Requires-Dist: mygene>=3.2.2; extra == "mygene"
Provides-Extra: enrichr
Requires-Dist: gseapy>=1.1.2; extra == "enrichr"
Provides-Extra: celltypist
Requires-Dist: celltypist>=1.5.0; extra == "celltypist"
Provides-Extra: integration
Requires-Dist: bbknn>=1.6.0; extra == "integration"
Provides-Extra: deseq2
Requires-Dist: rpy2>=3.5.10; extra == "deseq2"
Provides-Extra: semantic-dedup
Requires-Dist: sentence-transformers>=2.2.2; extra == "semantic-dedup"
Requires-Dist: faiss-cpu>=1.7.4; extra == "semantic-dedup"
Provides-Extra: all
Requires-Dist: mygene>=3.2.2; extra == "all"
Requires-Dist: gseapy>=1.1.2; extra == "all"
Requires-Dist: celltypist>=1.5.0; extra == "all"
Requires-Dist: bbknn>=1.6.0; extra == "all"
Requires-Dist: rpy2>=3.5.10; extra == "all"
Requires-Dist: sentence-transformers>=2.2.2; extra == "all"
Requires-Dist: faiss-cpu>=1.7.4; extra == "all"
